tiledb_jupyter_bioimg/__init__.py
tiledb_jupyter_bioimg/_frontend.py
tiledb_jupyter_bioimg/_version.py
tiledb_jupyter_bioimg/render.py
tiledb_jupyter_bioimg/labextension/package.json
tiledb_jupyter_bioimg/labextension/static/08450fe724517d116eb4.svg
tiledb_jupyter_bioimg/labextension/static/375.efd679afd10383345ffb.js
tiledb_jupyter_bioimg/labextension/static/375.efd679afd10383345ffb.js.LICENSE.txt
tiledb_jupyter_bioimg/labextension/static/446.3bf34f45c93ace9c0f28.js
tiledb_jupyter_bioimg/labextension/static/468.720ed03247c90f307866.js
tiledb_jupyter_bioimg/labextension/static/744.f5908170e1e7f6177d98.js
tiledb_jupyter_bioimg/labextension/static/747.6f54d04ff1f3fe09aea9.js
tiledb_jupyter_bioimg/labextension/static/995.7e5a9c38e396a47c7d4a.js
tiledb_jupyter_bioimg/labextension/static/995.7e5a9c38e396a47c7d4a.js.LICENSE.txt
tiledb_jupyter_bioimg/labextension/static/remoteEntry.bb430eda4a26b67784af.js
tiledb_jupyter_bioimg/labextension/static/style.js
tiledb_jupyter_bioimg/labextension/static/third-party-licenses.json
tiledb_jupyter_bioimg-0.2.1.data/data/share/jupyter/labextensions/@tiledb-inc/jupyter-bioimage-viewer/install.json
tiledb_jupyter_bioimg-0.2.1.data/data/share/jupyter/labextensions/@tiledb-inc/jupyter-bioimage-viewer/package.json
tiledb_jupyter_bioimg-0.2.1.data/data/share/jupyter/labextensions/@tiledb-inc/jupyter-bioimage-viewer/static/08450fe724517d116eb4.svg
tiledb_jupyter_bioimg-0.2.1.data/data/share/jupyter/labextensions/@tiledb-inc/jupyter-bioimage-viewer/static/375.efd679afd10383345ffb.js
tiledb_jupyter_bioimg-0.2.1.data/data/share/jupyter/labextensions/@tiledb-inc/jupyter-bioimage-viewer/static/375.efd679afd10383345ffb.js.LICENSE.txt
tiledb_jupyter_bioimg-0.2.1.data/data/share/jupyter/labextensions/@tiledb-inc/jupyter-bioimage-viewer/static/446.3bf34f45c93ace9c0f28.js
tiledb_jupyter_bioimg-0.2.1.data/data/share/jupyter/labextensions/@tiledb-inc/jupyter-bioimage-viewer/static/468.720ed03247c90f307866.js
tiledb_jupyter_bioimg-0.2.1.dist-info/LICENSE
tiledb_jupyter_bioimg-0.2.1.dist-info/METADATA
tiledb_jupyter_bioimg-0.2.1.dist-info/WHEEL
tiledb_jupyter_bioimg-0.2.1.dist-info/top_level.txt
tiledb_jupyter_bioimg-0.2.1.dist-info/RECORD
