Metadata-Version: 2.1
Name: tiledb-jupyter-bioimg
Version: 0.2.1
Summary: A jupyterlab extension to visualize bioimages in TileDB format
Home-page: https://github.com/TileDB-Inc/TileDB-Jupyter-BioImage-Viewer
Author: TileDB
License: BSD-3-Clause
Keywords: Jupyter,JupyterLab,JupyterLab3
Platform: Linux
Platform: Mac OS X
Platform: Windows
Classifier: License :: OSI Approved :: BSD License
Classifier: Programming Language :: Python
Classifier: Programming Language :: Python :: 3
Classifier: Programming Language :: Python :: 3.6
Classifier: Programming Language :: Python :: 3.7
Classifier: Programming Language :: Python :: 3.8
Classifier: Framework :: Jupyter
Requires-Python: >=3.6
License-File: LICENSE
Requires-Dist: ipywidgets >=7
